sevml/__init__.py
sevml/evaluation.py
sevml/explainability.py
sevml/main.py
sevml/preprocessing.py
sevml/training.py
sevml/visualization.py
sevml-0.4.1.dist-info/METADATA
sevml-0.4.1.dist-info/WHEEL
sevml-0.4.1.dist-info/entry_points.txt
sevml-0.4.1.dist-info/licenses/LICENSE
sevml-0.4.1.dist-info/RECORD
