Metadata-Version: 2.4
Name: sevml
Version: 0.4.1
Summary: Machine learning tools for biological analysis
Project-URL: Homepage, https://github.com
Project-URL: Issues, https://github.com
Author-email: Isen Naiken <isen_naiken@etu.u-bourgogne.fr>, Valentin Bosch <Valentin_Bosch@etu.u-bourgogne.fr>, Jessica Gobbo <jgobbo@cgfl.fr>
Maintainer-email: Isen Naiken <isen_naiken@etu.u-bourgogne.fr>
License-Expression: MIT
License-File: LICENSE
Classifier: Operating System :: OS Independent
Classifier: Programming Language :: Python :: 3
Requires-Python: >=3.8
Requires-Dist: matplotlib
Requires-Dist: numpy<2
Requires-Dist: pandas
Requires-Dist: scikit-learn
Requires-Dist: shap
Requires-Dist: xgboost
